[
    { "label": "Mr", "value": "Mr" },
    { "label": "Mrs", "value": "Mrs" },
    { "label": "Ms", "value": "Ms" },
    { "label": "Miss", "value": "Miss" },
    { "label": "Dr", "value": "Dr" },
    { "label": "Prof", "value": "Prof" },
    { "label": "Sir", "value": "Sir" },
    { "label": "Madam", "value": "Madam" },
    { "label": "Mx", "value": "Mx" },
    { "label": "Rev", "value": "Rev" },
    { "label": "Fr", "value": "Fr" },
    { "label": "Rabbi", "value": "Rabbi" },
    { "label": "Imam", "value": "Imam" },
    { "label": "Dame", "value": "Dame" },
    { "label": "Hon", "value": "Hon" },
    { "label": "Capt", "value": "Capt" },
    { "label": "Major", "value": "Major" },
    { "label": "Col", "value": "Col" },
    { "label": "Lt", "value": "Lt" },
    { "label": "Judge", "value": "Judge" },
    { "label": "Chief", "value": "Chief" }
  ]
  